dhamma/__init__.py
dhamma/main.py
dhamma-0.4.dist-info/METADATA
dhamma-0.4.dist-info/WHEEL
dhamma-0.4.dist-info/entry_points.txt
dhamma-0.4.dist-info/top_level.txt
dhamma-0.4.dist-info/RECORD
